pirateweather/__init__.py
pirateweather/api.py
pirateweather/models.py
pirateweather/utils.py
python_pirateweather-1.2.1.dist-info/licenses/LICENSE.txt
python_pirateweather-1.2.1.dist-info/METADATA
python_pirateweather-1.2.1.dist-info/WHEEL
python_pirateweather-1.2.1.dist-info/top_level.txt
python_pirateweather-1.2.1.dist-info/RECORD
