Metadata-Version: 2.4
Name: python-pirateweather
Version: 1.2.1
Summary: A thin Python Wrapper for the Pirate Weather API
Home-page: https://github.com/cloneofghosts/python-pirate-weather
Author: cloneofghosts
License: BSD 2-clause
Keywords: weather API wrapper pirateweather location
License-File: LICENSE.txt
Requires-Dist: requests==2.32.5
Dynamic: author
Dynamic: description
Dynamic: description-content-type
Dynamic: home-page
Dynamic: keywords
Dynamic: license
Dynamic: license-file
Dynamic: requires-dist
Dynamic: summary
